Metadata-Version: 1.1
Name: pysinonimos
Version: 0.1.1
Summary: API wrapper para busca de sinonimos
Home-page: https://github.com/diegofsousa/pysinonimos
Author: Diego F Sousa
Author-email: diegofernando5672@gmail.com
License: MIT License
Keywords: sinonimos portugues
Platform: UNKNOWN
Classifier: Development Status :: 3 - Alpha
Classifier: Intended Audience :: Developers
Classifier: Topic :: Software Development :: Build Tools
Classifier: License :: OSI Approved :: MIT License
Classifier: Programming Language :: Python :: 3
Classifier: Programming Language :: Python :: 3.2
Classifier: Programming Language :: Python :: 3.3
Classifier: Programming Language :: Python :: 3.4
Classifier: Programming Language :: Python :: 3.5
Classifier: Programming Language :: Python :: 3.6
